aggregateGithubCommits/__init__.py
aggregateGithubCommits/aggregateGithubCommits.py
tests/__init__.py
tests/conftest.py
tests/test_aggregate_commits.py
tests/test_check_args.py
tests/test_convert_to_csv.py
tests/test_convert_to_text.py
tests/test_extract_commits.py
tests/test_get_commits.py
tests/test_parse_args.py
aggregateGithubCommits-3.20200806.dist-info/LICENSE.md
aggregateGithubCommits-3.20200806.dist-info/LICENSE.rst
aggregateGithubCommits-3.20200806.dist-info/METADATA
aggregateGithubCommits-3.20200806.dist-info/WHEEL
aggregateGithubCommits-3.20200806.dist-info/entry_points.txt
aggregateGithubCommits-3.20200806.dist-info/top_level.txt
aggregateGithubCommits-3.20200806.dist-info/RECORD
