Metadata-Version: 2.1
Name: aggregateGithubCommits
Version: 3.20200806
Summary: aggregateGithubCommits: Aggregate Github commit count by author and time.
Home-page: https://github.com/rocaz/aggregateGithubCommits
Author: ROCA
Author-email: rocaznet@gmail.com
License: CC BY-NC-SA 4.0, non-commercial use only.
Keywords: github,github-api,commit,python3
Platform: UNKNOWN
Classifier: Development Status :: 5 - Production/Stable
Classifier: Environment :: Console
Classifier: Framework :: Pytest
Classifier: Intended Audience :: Developers
Classifier: Intended Audience :: System Administrators
Classifier: License :: Free for non-commercial use
Classifier: Natural Language :: English
Classifier: Programming Language :: Python
Classifier: Programming Language :: Python :: 3 :: Only
Classifier: Programming Language :: Python :: 3.7
Classifier: Programming Language :: Python :: 3.8
Classifier: Programming Language :: Python :: 3.9
Classifier: Topic :: Utilities
Requires-Python: >=3.7
Requires-Dist: pytz
Requires-Dist: tzlocal
Requires-Dist: python-dateutil
Requires-Dist: PyGithub
Requires-Dist: pandas
